{
  "version": "7",
  "dialect": "postgresql",
  "entries": [
    {
      "idx": 0,
      "version": "7",
      "when": 1763447873858,
      "tag": "0000_shocking_pretty_boy",
      "breakpoints": true
    },
    {
      "idx": 1,
      "version": "7",
      "when": 1763701939864,
      "tag": "0001_sparkling_lorna_dane",
      "breakpoints": true
    },
    {
      "idx": 2,
      "version": "7",
      "when": 1763702032984,
      "tag": "0002_boring_carmella_unuscione",
      "breakpoints": true
    },
    {
      "idx": 3,
      "version": "7",
      "when": 1766104464103,
      "tag": "0003_tired_multiple_man",
      "breakpoints": true
    },
    {
      "idx": 4,
      "version": "7",
      "when": 1768774330028,
      "tag": "0004_fixed_shooting_star",
      "breakpoints": true
    },
    {
      "idx": 5,
      "version": "7",
      "when": 1768780726553,
      "tag": "0005_opposite_wraith",
      "breakpoints": true
    },
    {
      "idx": 6,
      "version": "7",
      "when": 1768859109368,
      "tag": "0006_tidy_boomerang",
      "breakpoints": true
    }
  ]
}